Workbook

Sheet Consolidated IS
B1: Illustrative Group
B2: Consolidated income statement for the year ended 31 December 2025
B3: USD thousands
C5: 2025
B6: Revenue | C6: =-(Consolidation!I20+Consolidation!I21) -> 22124
B7: Cost of sales | C7: =-(Consolidation!I22+Consolidation!I23) -> -13048
B8: Gross profit | C8: =C6+C7 -> 9076
B9: Operating expenses | C9: =-Consolidation!I24 -> -4922
B10: Operating profit | C10: =C8+C9 -> 4154
B11: Interest expense | C11: =-Consolidation!I25 -> -372.7
B12: Profit before tax | C12: =C10+C11 -> 3781.3
B13: Income tax expense | C13: =-Consolidation!I26 -> -852.6
B14: Profit for the year | C14: =C12+C13 -> 2928.7
B16: Attributable to owners of the parent | C16: =C14-C17 -> 2834.96
B17: Attributable to non-controlling interests | C17: =(1-Inputs!$E$7)*-SUM(Translation!I17:I23)+(1-Inputs!$E$8)*-SUM(Translation!L17:L23) -> 93.74
B19: Unrealised profit is eliminated in full against the seller (Sub One, 100% owned), so it has no NCI effect.

Sheet Consolidated BS
B1: Illustrative Group
B2: Consolidated balance sheet at 31 December 2025
B3: USD thousands
C5: 2025
B6: Goodwill | C6: =Consolidation!I12 -> 500
B7: Property, plant and equipment | C7: =Consolidation!I10 -> 10444
B8: Total non-current assets | C8: =C6+C7 -> 10944
B9: Inventory | C9: =Consolidation!I9 -> 2690
B10: Trade receivables | C10: =Consolidation!I7 -> 3756
B11: Intercompany receivable (eliminated) | C11: =Consolidation!I8 -> 0
B12: Cash | C12: =Consolidation!I6 -> 2232
B13: Total current assets | C13: =SUM(C9:C12) -> 8678
B14: Total assets | C14: =C8+C13 -> 19622
B16: Share capital | C16: =-Consolidation!I16 -> 5000
B17: Retained earnings | C17: =-Consolidation!I17+'Consolidated IS'!C16 -> 5762.96
B18: Translation reserve | C18: =-Consolidation!I18 -> -24.56
B19: Equity attributable to owners of the parent | C19: =SUM(C16:C18) -> 10738.4
B20: Non-controlling interests | C20: =-Consolidation!I19+'Consolidated IS'!C17 -> 399.6
B21: Total equity | C21: =C19+C20 -> 11138
B22: Borrowings | C22: =-Consolidation!I15 -> 5648
B23: Trade payables | C23: =-Consolidation!I13 -> 2836
B24: Intercompany payable (eliminated) | C24: =-Consolidation!I14 -> 0
B25: Total liabilities | C25: =SUM(C22:C24) -> 8484
B26: Total equity and liabilities | C26: =C21+C25 -> 19622
B28: Check: assets less equity and liabilities | C28: =ROUND(C14-C26,2) -> 0

Sheet Consolidation
B1: Illustrative Group
B2: Consolidation worksheet (debit +, credit -)
B3: USD thousands
B5: Code | C5: Account | D5: PARENT (USD) | E5: SUB1 (USD) | F5: SUB2 (USD) | G5: Aggregate | H5: Eliminations | I5: Consolidated
B6: 1000 | C6: Cash | D6: =Translation!F6 -> 1200 | E6: =Translation!I6 -> 600 | F6: =Translation!L6 -> 432 | G6: =SUM(D6:F6) -> 2232 | H6: =SUMIFS(Eliminations!$F$6:$F$27,Eliminations!$D$6:$D$27,$B6) -> 0 | I6: =G6+H6 -> 2232
B7: 1100 | C7: Trade receivables | D7: =Translation!F7 -> 2100 | E7: =Translation!I7 -> 900 | F7: =Translation!L7 -> 756 | G7: =SUM(D7:F7) -> 3756 | H7: =SUMIFS(Eliminations!$F$6:$F$27,Eliminations!$D$6:$D$27,$B7) -> 0 | I7: =G7+H7 -> 3756
B8: 1150 | C8: Intercompany receivable | D8: =Translation!F8 -> 540 | E8: =Translation!I8 -> 150 | F8: =Translation!L8 -> 0 | G8: =SUM(D8:F8) -> 690 | H8: =SUMIFS(Eliminations!$F$6:$F$27,Eliminations!$D$6:$D$27,$B8) -> -690 | I8: =G8+H8 -> 0
B9: 1200 | C9: Inventory | D9: =Translation!F9 -> 1500 | E9: =Translation!I9 -> 700 | F9: =Translation!L9 -> 540 | G9: =SUM(D9:F9) -> 2740 | H9: =SUMIFS(Eliminations!$F$6:$F$27,Eliminations!$D$6:$D$27,$B9) -> -50 | I9: =G9+H9 -> 2690
B10: 1500 | C10: Property, plant and equipment | D10: =Translation!F10 -> 6000 | E10: =Translation!I10 -> 2500 | F10: =Translation!L10 -> 1944 | G10: =SUM(D10:F10) -> 10444 | H10: =SUMIFS(Eliminations!$F$6:$F$27,Eliminations!$D$6:$D$27,$B10) -> 0 | I10: =G10+H10 -> 10444
B11: 1600 | C11: Investment in subsidiaries | D11: =Translation!F11 -> 3580 | E11: =Translation!I11 -> 0 | F11: =Translation!L11 -> 0 | G11: =SUM(D11:F11) -> 3580 | H11: =SUMIFS(Eliminations!$F$6:$F$27,Eliminations!$D$6:$D$27,$B11) -> -3580 | I11: =G11+H11 -> 0
B12: 1700 | C12: Goodwill | D12: 0 | E12: 0 | F12: 0 | G12: =SUM(D12:F12) -> 0 | H12: =SUMIFS(Eliminations!$F$6:$F$27,Eliminations!$D$6:$D$27,$B12) -> 500 | I12: =G12+H12 -> 500
B13: 2000 | C13: Trade payables | D13: =Translation!F12 -> -1700 | E13: =Translation!I12 -> -650 | F13: =Translation!L12 -> -486 | G13: =SUM(D13:F13) -> -2836 | H13: =SUMIFS(Eliminations!$F$6:$F$27,Eliminations!$D$6:$D$27,$B13) -> 0 | I13: =G13+H13 -> -2836
B14: 2150 | C14: Intercompany payable | D14: =Translation!F13 -> -150 | E14: =Translation!I13 -> 0 | F14: =Translation!L13 -> -540 | G14: =SUM(D14:F14) -> -690 | H14: =SUMIFS(Eliminations!$F$6:$F$27,Eliminations!$D$6:$D$27,$B14) -> 690 | I14: =G14+H14 -> 0
B15: 2500 | C15: Borrowings | D15: =Translation!F14 -> -4000 | E15: =Translation!I14 -> -1000 | F15: =Translation!L14 -> -648 | G15: =SUM(D15:F15) -> -5648 | H15: =SUMIFS(Eliminations!$F$6:$F$27,Eliminations!$D$6:$D$27,$B15) -> 0 | I15: =G15+H15 -> -5648
B16: 3000 | C16: Share capital | D16: =Translation!F15 -> -5000 | E16: =Translation!I15 -> -1000 | F16: =Translation!L15 -> -1100 | G16: =SUM(D16:F16) -> -7100 | H16: =SUMIFS(Eliminations!$F$6:$F$27,Eliminations!$D$6:$D$27,$B16) -> 2100 | I16: =G16+H16 -> -5000
B17: 3100 | C17: Retained earnings (opening) | D17: =Translation!F16 -> -2300 | E17: =Translation!I16 -> -1460 | F17: =Translation!L16 -> -460 | G17: =SUM(D17:F17) -> -4220 | H17: =SUMIFS(Eliminations!$F$6:$F$27,Eliminations!$D$6:$D$27,$B17) -> 1292 | I17: =G17+H17 -> -2928
B18: 3200 | C18: Translation reserve | D18: =Translation!F24 -> 0 | E18: =Translation!I24 -> 0 | F18: =Translation!L24 -> 30.7 | G18: =SUM(D18:F18) -> 30.7 | H18: =SUMIFS(Eliminations!$F$6:$F$27,Eliminations!$D$6:$D$27,$B18) -> -6.14 | I18: =G18+H18 -> 24.56
B19: 3300 | C19: Non-controlling interests | D19: 0 | E19: 0 | F19: 0 | G19: =SUM(D19:F19) -> 0 | H19: =SUMIFS(Eliminations!$F$6:$F$27,Eliminations!$D$6:$D$27,$B19) -> -305.86 | I19: =G19+H19 -> -305.86
B20: 4000 | C20: Revenue | D20: =Translation!F17 -> -14000 | E20: =Translation!I17 -> -4200 | F20: =Translation!L17 -> -3924 | G20: =SUM(D20:F20) -> -22124 | H20: =SUMIFS(Eliminations!$F$6:$F$27,Eliminations!$D$6:$D$27,$B20) -> 0 | I20: =G20+H20 -> -22124
B21: 4050 | C21: Intercompany revenue | D21: =Translation!F18 -> 0 | E21: =Translation!I18 -> -800 | F21: =Translation!L18 -> 0 | G21: =SUM(D21:F21) -> -800 | H21: =SUMIFS(Eliminations!$F$6:$F$27,Eliminations!$D$6:$D$27,$B21) -> 800 | I21: =G21+H21 -> 0
B22: 5000 | C22: Cost of sales | D22: =Translation!F19 -> 7600 | E22: =Translation!I19 -> 3000 | F22: =Translation!L19 -> 2398 | G22: =SUM(D22:F22) -> 12998 | H22: =SUMIFS(Eliminations!$F$6:$F$27,Eliminations!$D$6:$D$27,$B22) -> 50 | I22: =G22+H22 -> 13048
B23: 5050 | C23: Intercompany purchases | D23: =Translation!F20 -> 800 | E23: =Translation!I20 -> 0 | F23: =Translation!L20 -> 0 | G23: =SUM(D23:F23) -> 800 | H23: =SUMIFS(Eliminations!$F$6:$F$27,Eliminations!$D$6:$D$27,$B23) -> -800 | I23: =G23+H23 -> 0
B24: 6000 | C24: Operating expenses | D24: =Translation!F21 -> 3100 | E24: =Translation!I21 -> 950 | F24: =Translation!L21 -> 872 | G24: =SUM(D24:F24) -> 4922 | H24: =SUMIFS(Eliminations!$F$6:$F$27,Eliminations!$D$6:$D$27,$B24) -> 0 | I24: =G24+H24 -> 4922
B25: 7000 | C25: Interest expense | D25: =Translation!F22 -> 280 | E25: =Translation!I22 -> 60 | F25: =Translation!L22 -> 32.7 | G25: =SUM(D25:F25) -> 372.7 | H25: =SUMIFS(Eliminations!$F$6:$F$27,Eliminations!$D$6:$D$27,$B25) -> 0 | I25: =G25+H25 -> 372.7
B26: 8000 | C26: Income tax expense | D26: =Translation!F23 -> 450 | E26: =Translation!I23 -> 250 | F26: =Translation!L23 -> 152.6 | G26: =SUM(D26:F26) -> 852.6 | H26: =SUMIFS(Eliminations!$F$6:$F$27,Eliminations!$D$6:$D$27,$B26) -> 0 | I26: =G26+H26 -> 852.6
C27: Check (should be zero) | D27: =ROUND(SUM(D6:D26),2) -> 0 | E27: =ROUND(SUM(E6:E26),2) -> 0 | F27: =ROUND(SUM(F6:F26),2) -> 0 | G27: =ROUND(SUM(G6:G26),2) -> 0 | H27: =ROUND(SUM(H6:H26),2) -> 0 | I27: =ROUND(SUM(I6:I26),2) -> 0

Sheet Eliminations
B1: Illustrative Group
B2: Consolidation adjustments (debit +, credit -)
B3: USD thousands
B5: # | C5: Description | D5: Code | E5: Account | F5: Amount
B6: 1 | C6: Investment in Subsidiary One (US) | D6: 3000 | E6: Share capital | F6: =(-Translation!I15) -> 1000
B7: 1 | C7: Investment in Subsidiary One (US) | D7: 3100 | E7: Retained earnings (opening) | F7: =Inputs!$G$7 -> 1200
B8: 1 | C8: Investment in Subsidiary One (US) | D8: 1700 | E8: Goodwill | F8: =Inputs!$F$7-Inputs!$E$7*((-Translation!I15)+Inputs!$G$7) -> 500
B9: 1 | C9: Investment in Subsidiary One (US) | D9: 1600 | E9: Investment in subsidiaries | F9: =-Inputs!$F$7 -> -2700
B10: 1 | C10: Investment in Subsidiary One (US) | D10: 3300 | E10: Non-controlling interests | F10: =-(1-Inputs!$E$7)*((-Translation!I15)+Inputs!$G$7) -> 0
B11: 2 | C11: Investment in Subsidiary Two (Germany) | D11: 3000 | E11: Share capital | F11: =(-Translation!L15) -> 1100
B12: 2 | C12: Investment in Subsidiary Two (Germany) | D12: 3100 | E12: Retained earnings (opening) | F12: =Inputs!$G$8 -> 0
B13: 2 | C13: Investment in Subsidiary Two (Germany) | D13: 1700 | E13: Goodwill | F13: =Inputs!$F$8-Inputs!$E$8*((-Translation!L15)+Inputs!$G$8) -> 0
B14: 2 | C14: Investment in Subsidiary Two (Germany) | D14: 1600 | E14: Investment in subsidiaries | F14: =-Inputs!$F$8 -> -880
B15: 2 | C15: Investment in Subsidiary Two (Germany) | D15: 3300 | E15: Non-controlling interests | F15: =-(1-Inputs!$E$8)*((-Translation!L15)+Inputs!$G$8) -> -220
B16: 3 | C16: NCI share of Subsidiary Two (Germany) post-acquisition reserves | D16: 3100 | E16: Retained earnings (opening) | F16: =(1-Inputs!$E$8)*(-Translation!L16-Inputs!$G$8) -> 92
B17: 3 | C17: NCI share of Subsidiary Two (Germany) post-acquisition reserves | D17: 3300 | E17: Non-controlling interests | F17: =-(1-Inputs!$E$8)*(-Translation!L16-Inputs!$G$8) -> -92
B18: 3 | C18: NCI share of Subsidiary Two (Germany) post-acquisition reserves | D18: 3200 | E18: Translation reserve | F18: =-(1-Inputs!$E$8)*Translation!L24 -> -6.14
B19: 3 | C19: NCI share of Subsidiary Two (Germany) post-acquisition reserves | D19: 3300 | E19: Non-controlling interests | F19: =(1-Inputs!$E$8)*Translation!L24 -> 6.14
B20: 4 | C20: Intercompany balance: Parent owes Sub One for goods bought | D20: 2150 | E20: Intercompany payable | F20: =Inputs!$F$17 -> 150
B21: 4 | C21: Intercompany balance: Parent owes Sub One for goods bought | D21: 1150 | E21: Intercompany receivable | F21: =-Inputs!$F$17 -> -150
B22: 5 | C22: Intercompany balance: Loan from Parent to Sub Two (EUR 500) | D22: 2150 | E22: Intercompany payable | F22: =Inputs!$F$18 -> 540
B23: 5 | C23: Intercompany balance: Loan from Parent to Sub Two (EUR 500) | D23: 1150 | E23: Intercompany receivable | F23: =-Inputs!$F$18 -> -540
B24: 6 | C24: Intercompany sale: Goods sold by Sub One to Parent | D24: 4050 | E24: Intercompany revenue | F24: =Inputs!$F$19 -> 800
B25: 6 | C25: Intercompany sale: Goods sold by Sub One to Parent | D25: 5050 | E25: Intercompany purchases | F25: =-Inputs!$F$19 -> -800
B26: 7 | C26: Unrealised profit in inventory: Parent still holds 200 of goods from Sub One; Sub One margin 25% | D26: 5000 | E26: Cost of sales | F26: =Inputs!$F$20 -> 50
B27: 7 | C27: Unrealised profit in inventory: Parent still holds 200 of goods from Sub One; Sub One margin 25% | D27: 1200 | E27: Inventory | F27: =-Inputs!$F$20 -> -50
E28: Total (should be zero) | F28: =ROUND(SUM(F6:F27),2) -> 0

Sheet Translation
B1: Illustrative Group
B2: Translation into USD
B3: USD thousands
B5: Code | C5: Account | D5: PARENT local | E5: PARENT rate | F5: PARENT USD | G5: SUB1 local | H5: SUB1 rate | I5: SUB1 USD | J5: SUB2 local | K5: SUB2 rate | L5: SUB2 USD
B6: 1000 | C6: Cash | D6: ='Trial Balances'!E6 -> 1200 | E6: =Inputs!$D$12 -> 1 | F6: =D6*E6 -> 1200 | G6: ='Trial Balances'!F6 -> 600 | H6: =Inputs!$D$12 -> 1 | I6: =G6*H6 -> 600 | J6: ='Trial Balances'!G6 -> 400 | K6: =Inputs!$D$13 -> 1.08 | L6: =J6*K6 -> 432
B7: 1100 | C7: Trade receivables | D7: ='Trial Balances'!E7 -> 2100 | E7: =Inputs!$D$12 -> 1 | F7: =D7*E7 -> 2100 | G7: ='Trial Balances'!F7 -> 900 | H7: =Inputs!$D$12 -> 1 | I7: =G7*H7 -> 900 | J7: ='Trial Balances'!G7 -> 700 | K7: =Inputs!$D$13 -> 1.08 | L7: =J7*K7 -> 756
B8: 1150 | C8: Intercompany receivable | D8: ='Trial Balances'!E8 -> 540 | E8: =Inputs!$D$12 -> 1 | F8: =D8*E8 -> 540 | G8: ='Trial Balances'!F8 -> 150 | H8: =Inputs!$D$12 -> 1 | I8: =G8*H8 -> 150 | J8: ='Trial Balances'!G8 -> 0 | K8: =Inputs!$D$13 -> 1.08 | L8: =J8*K8 -> 0
B9: 1200 | C9: Inventory | D9: ='Trial Balances'!E9 -> 1500 | E9: =Inputs!$D$12 -> 1 | F9: =D9*E9 -> 1500 | G9: ='Trial Balances'!F9 -> 700 | H9: =Inputs!$D$12 -> 1 | I9: =G9*H9 -> 700 | J9: ='Trial Balances'!G9 -> 500 | K9: =Inputs!$D$13 -> 1.08 | L9: =J9*K9 -> 540
B10: 1500 | C10: Property, plant and equipment | D10: ='Trial Balances'!E10 -> 6000 | E10: =Inputs!$D$12 -> 1 | F10: =D10*E10 -> 6000 | G10: ='Trial Balances'!F10 -> 2500 | H10: =Inputs!$D$12 -> 1 | I10: =G10*H10 -> 2500 | J10: ='Trial Balances'!G10 -> 1800 | K10: =Inputs!$D$13 -> 1.08 | L10: =J10*K10 -> 1944
B11: 1600 | C11: Investment in subsidiaries | D11: ='Trial Balances'!E11 -> 3580 | E11: =Inputs!$D$12 -> 1 | F11: =D11*E11 -> 3580 | G11: ='Trial Balances'!F11 -> 0 | H11: =Inputs!$D$12 -> 1 | I11: =G11*H11 -> 0 | J11: ='Trial Balances'!G11 -> 0 | K11: =Inputs!$D$13 -> 1.08 | L11: =J11*K11 -> 0
B12: 2000 | C12: Trade payables | D12: ='Trial Balances'!E12 -> -1700 | E12: =Inputs!$D$12 -> 1 | F12: =D12*E12 -> -1700 | G12: ='Trial Balances'!F12 -> -650 | H12: =Inputs!$D$12 -> 1 | I12: =G12*H12 -> -650 | J12: ='Trial Balances'!G12 -> -450 | K12: =Inputs!$D$13 -> 1.08 | L12: =J12*K12 -> -486
B13: 2150 | C13: Intercompany payable | D13: ='Trial Balances'!E13 -> -150 | E13: =Inputs!$D$12 -> 1 | F13: =D13*E13 -> -150 | G13: ='Trial Balances'!F13 -> 0 | H13: =Inputs!$D$12 -> 1 | I13: =G13*H13 -> 0 | J13: ='Trial Balances'!G13 -> -500 | K13: =Inputs!$D$13 -> 1.08 | L13: =J13*K13 -> -540
B14: 2500 | C14: Borrowings | D14: ='Trial Balances'!E14 -> -4000 | E14: =Inputs!$D$12 -> 1 | F14: =D14*E14 -> -4000 | G14: ='Trial Balances'!F14 -> -1000 | H14: =Inputs!$D$12 -> 1 | I14: =G14*H14 -> -1000 | J14: ='Trial Balances'!G14 -> -600 | K14: =Inputs!$D$13 -> 1.08 | L14: =J14*K14 -> -648
B15: 3000 | C15: Share capital | D15: ='Trial Balances'!E15 -> -5000 | E15: =Inputs!$F$12 -> 1 | F15: =D15*E15 -> -5000 | G15: ='Trial Balances'!F15 -> -1000 | H15: =Inputs!$F$12 -> 1 | I15: =G15*H15 -> -1000 | J15: ='Trial Balances'!G15 -> -1000 | K15: =Inputs!$F$13 -> 1.1 | L15: =J15*K15 -> -1100
B16: 3100 | C16: Retained earnings (opening) | D16: ='Trial Balances'!E16 -> -2300 | E16: =Inputs!$F$12 -> 1 | F16: =D16*E16 -> -2300 | G16: ='Trial Balances'!F16 -> -1460 | H16: =Inputs!$F$12 -> 1 | I16: =G16*H16 -> -1460 | J16: ='Trial Balances'!G16 -> -420 | K16: =IF(J16=0,0,L16/J16) -> 1.0952381 | L16: =-Inputs!$H$8 -> -460
B17: 4000 | C17: Revenue | D17: ='Trial Balances'!E17 -> -14000 | E17: =Inputs!$E$12 -> 1 | F17: =D17*E17 -> -14000 | G17: ='Trial Balances'!F17 -> -4200 | H17: =Inputs!$E$12 -> 1 | I17: =G17*H17 -> -4200 | J17: ='Trial Balances'!G17 -> -3600 | K17: =Inputs!$E$13 -> 1.09 | L17: =J17*K17 -> -3924
B18: 4050 | C18: Intercompany revenue | D18: ='Trial Balances'!E18 -> 0 | E18: =Inputs!$E$12 -> 1 | F18: =D18*E18 -> 0 | G18: ='Trial Balances'!F18 -> -800 | H18: =Inputs!$E$12 -> 1 | I18: =G18*H18 -> -800 | J18: ='Trial Balances'!G18 -> 0 | K18: =Inputs!$E$13 -> 1.09 | L18: =J18*K18 -> 0
B19: 5000 | C19: Cost of sales | D19: ='Trial Balances'!E19 -> 7600 | E19: =Inputs!$E$12 -> 1 | F19: =D19*E19 -> 7600 | G19: ='Trial Balances'!F19 -> 3000 | H19: =Inputs!$E$12 -> 1 | I19: =G19*H19 -> 3000 | J19: ='Trial Balances'!G19 -> 2200 | K19: =Inputs!$E$13 -> 1.09 | L19: =J19*K19 -> 2398
B20: 5050 | C20: Intercompany purchases | D20: ='Trial Balances'!E20 -> 800 | E20: =Inputs!$E$12 -> 1 | F20: =D20*E20 -> 800 | G20: ='Trial Balances'!F20 -> 0 | H20: =Inputs!$E$12 -> 1 | I20: =G20*H20 -> 0 | J20: ='Trial Balances'!G20 -> 0 | K20: =Inputs!$E$13 -> 1.09 | L20: =J20*K20 -> 0
B21: 6000 | C21: Operating expenses | D21: ='Trial Balances'!E21 -> 3100 | E21: =Inputs!$E$12 -> 1 | F21: =D21*E21 -> 3100 | G21: ='Trial Balances'!F21 -> 950 | H21: =Inputs!$E$12 -> 1 | I21: =G21*H21 -> 950 | J21: ='Trial Balances'!G21 -> 800 | K21: =Inputs!$E$13 -> 1.09 | L21: =J21*K21 -> 872
B22: 7000 | C22: Interest expense | D22: ='Trial Balances'!E22 -> 280 | E22: =Inputs!$E$12 -> 1 | F22: =D22*E22 -> 280 | G22: ='Trial Balances'!F22 -> 60 | H22: =Inputs!$E$12 -> 1 | I22: =G22*H22 -> 60 | J22: ='Trial Balances'!G22 -> 30 | K22: =Inputs!$E$13 -> 1.09 | L22: =J22*K22 -> 32.7
B23: 8000 | C23: Income tax expense | D23: ='Trial Balances'!E23 -> 450 | E23: =Inputs!$E$12 -> 1 | F23: =D23*E23 -> 450 | G23: ='Trial Balances'!F23 -> 250 | H23: =Inputs!$E$12 -> 1 | I23: =G23*H23 -> 250 | J23: ='Trial Balances'!G23 -> 140 | K23: =Inputs!$E$13 -> 1.09 | L23: =J23*K23 -> 152.6
B24: 3200 | C24: Translation reserve | F24: =-SUM(F6:F23) -> 0 | I24: =-SUM(I6:I23) -> 0 | L24: =-SUM(L6:L23) -> 30.7
B26: Assets and liabilities at closing rate, income and expenses at average rate, share capital at historical rate, opening retained earnings at the USD amount carried forward. The translation reserve balances the translated trial balance.

Sheet Trial Balances
B1: Illustrative Group
B2: Entity trial balances in local currency (debit +, credit -)
B3: thousands of local currency
B5: Code | C5: Account | D5: Type | E5: PARENT (USD) | F5: SUB1 (USD) | G5: SUB2 (EUR)
B6: 1000 | C6: Cash | D6: A | E6: 1200 | F6: 600 | G6: 400
B7: 1100 | C7: Trade receivables | D7: A | E7: 2100 | F7: 900 | G7: 700
B8: 1150 | C8: Intercompany receivable | D8: A | E8: 540 | F8: 150 | G8: 0
B9: 1200 | C9: Inventory | D9: A | E9: 1500 | F9: 700 | G9: 500
B10: 1500 | C10: Property, plant and equipment | D10: A | E10: 6000 | F10: 2500 | G10: 1800
B11: 1600 | C11: Investment in subsidiaries | D11: A | E11: 3580 | F11: 0 | G11: 0
B12: 2000 | C12: Trade payables | D12: L | E12: -1700 | F12: -650 | G12: -450
B13: 2150 | C13: Intercompany payable | D13: L | E13: -150 | F13: 0 | G13: -500
B14: 2500 | C14: Borrowings | D14: L | E14: -4000 | F14: -1000 | G14: -600
B15: 3000 | C15: Share capital | D15: E | E15: -5000 | F15: -1000 | G15: -1000
B16: 3100 | C16: Retained earnings (opening) | D16: E | E16: -2300 | F16: -1460 | G16: -420
B17: 4000 | C17: Revenue | D17: I | E17: -14000 | F17: -4200 | G17: -3600
... B23: 8000 | C23: Income tax expense | D23: X | E23: 450 | F23: 250 | G23: 140
C24: Check (should be zero) | E24: =SUM(E6:E23) -> 0 | F24: =SUM(F6:F23) -> 0 | G24: =SUM(G6:G23) -> 0

Sheet Inputs
B1: Illustrative Group
B2: Group structure, exchange rates and intercompany data
B3: USD thousands
B5: Entity | C5: Name | D5: Currency | E5: Ownership | F5: Investment cost | G5: Pre-acq. retained earnings | H5: Opening RE (USD)
B6: PARENT | C6: Parent Co. | D6: USD | E6: 1 | F6: 0 | G6: 0
B7: SUB1 | C7: Subsidiary One (US) | D7: USD | E7: 1 | F7: 2700 | G7: 1200
B8: SUB2 | C8: Subsidiary Two (Germany) | D8: EUR | E8: 0.8 | F8: 880 | G8: 0 | H8: 460
B11: Currency | D11: Closing | E11: Average | F11: Historical
B12: USD | D12: 1 | E12: 1 | F12: 1
B13: EUR | D13: 1.08 | E13: 1.09 | F13: 1.1
B16: Type | C16: Description | D16: From | E16: To | F16: Amount (USD)
B17: balance | C17: Parent owes Sub One for goods bought | D17: SUB1 | E17: PARENT | F17: 150
B18: balance | C18: Loan from Parent to Sub Two (EUR 500) | D18: PARENT | E18: SUB2 | F18: 540
B19: sale | C19: Goods sold by Sub One to Parent | D19: SUB1 | E19: PARENT | F19: 800
B20: unrealised_profit | C20: Parent still holds 200 of goods from Sub One; Sub One margin 25% | D20: SUB1 | E20: PARENT | F20: 50

Sheet Checks
B1: Illustrative Group
B2: Checks (all should be zero)
B3: USD thousands
B6: Entity trial balances balance | C6: =ROUND(ABS('Trial Balances'!E24)+ABS('Trial Balances'!F24)+ABS('Trial Balances'!G24),2) -> 0
B7: Elimination journal balances | C7: =ROUND(ABS(Eliminations!F28),2) -> 0
B8: Consolidation worksheet balances | C8: =ROUND(ABS(Consolidation!I27),2) -> 0
B9: Intercompany receivables and payables fully eliminated | C9: =ROUND(ABS(Consolidation!I8)+ABS(Consolidation!I14),2) -> 0
B10: Intercompany sales and purchases fully eliminated | C10: =ROUND(ABS(Consolidation!I21)+ABS(Consolidation!I23),2) -> 0
B11: Balance sheet balances | C11: =ROUND(ABS('Consolidated BS'!C28),2) -> 0
B13: All checks pass? | C13: =IF(SUM(C6:C11)=0,"OK","ERROR") -> OK
